pointframes/__init__.py
pointframes/core/__init__.py
pointframes/core/dataframe_tools.py
pointframes/core/pointcloud.py
pointframes/dl_models/__init__.py
pointframes/dl_models/mccnn.py
pointframes/dl_models/mccnnSCANNET.py
pointframes/dl_models/pointnet.py
pointframes/dl_models/pointnet2.py
pointframes/dl_models/mccnn_utils/MCCNNDataSet.py
pointframes/dl_models/mccnn_utils/MCCNNDataSetSN.py
pointframes/dl_models/mccnn_utils/__init__.py
pointframes/dl_models/mccnn_utils/inference_seg.py
pointframes/dl_models/mccnn_utils/inference_sn.py
pointframes/dl_models/mccnn_utils/train_seg.py
pointframes/dl_models/mccnn_utils/train_sn.py
pointframes/dl_models/pointnet2_utils/__init__.py
pointframes/dl_models/pointnet2_utils/inference.py
pointframes/dl_models/pointnet2_utils/pc_util.py
pointframes/dl_models/pointnet2_utils/pointnet2_model.py
pointframes/dl_models/pointnet2_utils/train.py
pointframes/dl_models/pointnet2_utils/utils/__init__.py
pointframes/dl_models/pointnet2_utils/utils/eulerangles.py
pointframes/dl_models/pointnet2_utils/utils/pc_util.py
pointframes/dl_models/pointnet2_utils/utils/plyfile.py
pointframes/dl_models/pointnet2_utils/utils/pointnet_util.py
pointframes/dl_models/pointnet2_utils/utils/provider.py
pointframes/dl_models/pointnet2_utils/utils/tf_util2.py
pointframes/dl_models/pointnet_utils/__init__.py
pointframes/dl_models/pointnet_utils/inference.py
pointframes/dl_models/pointnet_utils/train.py
pointframes/dl_models/pointnet_utils/utils/__init__.py
pointframes/dl_models/pointnet_utils/utils/eulerangles.py
pointframes/dl_models/pointnet_utils/utils/pc_util.py
pointframes/dl_models/pointnet_utils/utils/pointnet_model.py
pointframes/dl_models/pointnet_utils/utils/provider.py
pointframes/dl_models/pointnet_utils/utils/tf_util.py
pointframes/features/__init__.py
pointframes/features/eigenvectors.py
pointframes/indexing/__init__.py
pointframes/indexing/index.py
pointframes/indexing/zorder.py
pointframes-0.0.3.dist-info/METADATA
pointframes-0.0.3.dist-info/RECORD
pointframes-0.0.3.dist-info/WHEEL
pointframes-0.0.3.dist-info/top_level.txt
