Metadata-Version: 2.1
Name: pointframes
Version: 0.0.3
Summary: PointFrames - A Scalable Point Code Library
Home-page: https://github.com/3Dimaging-ucl/pointframes
Author: David Griffiths
Author-email: david.griffiths.16@ucl.ac.uk
License: UNKNOWN
Platform: UNKNOWN
Requires-Dist: open3d-python
Requires-Dist: numpy
Requires-Dist: pandas
Requires-Dist: pyarrow
Requires-Dist: tables
Requires-Dist: scikit-learn
Requires-Dist: dask[array]
Requires-Dist: dask[dataframe]
Requires-Dist: dask[distributed]
Requires-Dist: matplotlib
Requires-Dist: h5py
Requires-Dist: progressbar
